{"chunk_definitions":[{"row":96,"row_count":1,"visible":true,"expansion_state":0,"options":{"engine":"r","eval":false,"label":"unnamed-chunk-14"},"document_id":"8BFB1351","chunk_id":"c17q9leu5hb0j","chunk_label":"unnamed-chunk-3"},{"row":112,"row_count":1,"visible":true,"expansion_state":0,"options":{"engine":"r","label":"unnamed-chunk-15"},"document_id":"8BFB1351","chunk_id":"cpx5wyd90h7lp","chunk_label":"unnamed-chunk-4"},{"row":219,"row_count":1,"visible":true,"expansion_state":0,"options":{"engine":"r","label":"unnamed-chunk-18"},"document_id":"8BFB1351","chunk_id":"ciue6be3qwvkp","chunk_label":"unnamed-chunk-9"},{"row":232,"row_count":1,"visible":true,"expansion_state":0,"options":{"engine":"r","label":"unnamed-chunk-22"},"document_id":"8BFB1351","chunk_id":"cc401pm6ffq8r","chunk_label":"unnamed-chunk-11"}],"doc_write_time":1749587420}